PythonZhinengXiangmuChuyiFix1/README.md
PythonZhinengXiangmuChuyiFix1/__init__.py
PythonZhinengXiangmuChuyiFix1/__main__.py
PythonZhinengXiangmuChuyiFix1/file.epub
PythonZhinengXiangmuChuyiFix1/index.html
PythonZhinengXiangmuChuyiFix1/css/__init__.py
PythonZhinengXiangmuChuyiFix1/css/annotations.css
PythonZhinengXiangmuChuyiFix1/css/main.css
PythonZhinengXiangmuChuyiFix1/css/normalize.css
PythonZhinengXiangmuChuyiFix1/css/popup.css
PythonZhinengXiangmuChuyiFix1/font/__init__.py
PythonZhinengXiangmuChuyiFix1/font/fontello.eot
PythonZhinengXiangmuChuyiFix1/font/fontello.svg
PythonZhinengXiangmuChuyiFix1/font/fontello.ttf
PythonZhinengXiangmuChuyiFix1/font/fontello.woff
PythonZhinengXiangmuChuyiFix1/img/__init__.py
PythonZhinengXiangmuChuyiFix1/img/annotator-glyph-sprite.png
PythonZhinengXiangmuChuyiFix1/img/annotator-icon-sprite.png
PythonZhinengXiangmuChuyiFix1/img/apple-touch-icon.png
PythonZhinengXiangmuChuyiFix1/img/cancelfullscreen.png
PythonZhinengXiangmuChuyiFix1/img/close.png
PythonZhinengXiangmuChuyiFix1/img/fullscreen.png
PythonZhinengXiangmuChuyiFix1/img/loader.gif
PythonZhinengXiangmuChuyiFix1/img/menu-icon.png
PythonZhinengXiangmuChuyiFix1/img/save.png
PythonZhinengXiangmuChuyiFix1/img/saved.png
PythonZhinengXiangmuChuyiFix1/img/settings-s.png
PythonZhinengXiangmuChuyiFix1/img/settings.png
PythonZhinengXiangmuChuyiFix1/img/star.png
PythonZhinengXiangmuChuyiFix1/js/__init__.py
PythonZhinengXiangmuChuyiFix1/js/epub.js
PythonZhinengXiangmuChuyiFix1/js/epub.min.js
PythonZhinengXiangmuChuyiFix1/js/epub.min.map
PythonZhinengXiangmuChuyiFix1/js/hooks.min.js
PythonZhinengXiangmuChuyiFix1/js/hooks.min.map
PythonZhinengXiangmuChuyiFix1/js/reader.js
PythonZhinengXiangmuChuyiFix1/js/reader.js.map
PythonZhinengXiangmuChuyiFix1/js/reader.min.js
PythonZhinengXiangmuChuyiFix1/js/reader.min.map
PythonZhinengXiangmuChuyiFix1/js/hooks/__init__.py
PythonZhinengXiangmuChuyiFix1/js/hooks/extensions/__init__.py
PythonZhinengXiangmuChuyiFix1/js/hooks/extensions/highlight.js
python_zhineng_xiangmu_chuyi_fix1-2025.3.25.1.dist-info/METADATA
python_zhineng_xiangmu_chuyi_fix1-2025.3.25.1.dist-info/WHEEL
python_zhineng_xiangmu_chuyi_fix1-2025.3.25.1.dist-info/entry_points.txt
python_zhineng_xiangmu_chuyi_fix1-2025.3.25.1.dist-info/top_level.txt
python_zhineng_xiangmu_chuyi_fix1-2025.3.25.1.dist-info/RECORD
